slack/__init__.py
slack/errors.py
slack/py.typed
slack/version.py
slack/rtm/__init__.py
slack/rtm/client.py
slack/signature/__init__.py
slack/signature/verifier.py
slack/web/__init__.py
slack/web/async_base_client.py
slack/web/async_client.py
slack/web/async_internal_utils.py
slack/web/async_slack_response.py
slack/web/base_client.py
slack/web/client.py
slack/web/deprecation.py
slack/web/internal_utils.py
slack/web/slack_response.py
slack/web/classes/__init__.py
slack/web/classes/actions.py
slack/web/classes/attachments.py
slack/web/classes/blocks.py
slack/web/classes/dialog_elements.py
slack/web/classes/dialogs.py
slack/web/classes/elements.py
slack/web/classes/interactions.py
slack/web/classes/messages.py
slack/web/classes/objects.py
slack/web/classes/views.py
slack/webhook/__init__.py
slack/webhook/async_client.py
slack/webhook/client.py
slack/webhook/internal_utils.py
slack/webhook/webhook_response.py
slackclient-2.9.4.dist-info/LICENSE
slackclient-2.9.4.dist-info/METADATA
slackclient-2.9.4.dist-info/WHEEL
slackclient-2.9.4.dist-info/top_level.txt
slackclient-2.9.4.dist-info/RECORD
