Metadata-Version: 2.1
Name: slackclient
Version: 2.9.4
Summary: Slack API clients for Web API and RTM API (Legacy) - Please use https://pypi.org/project/slack-sdk/ instead.
Home-page: https://github.com/slackapi/python-slack-sdk
Author: Slack Technologies, LLC
Author-email: opensource@slack.com
License: MIT
Keywords: slack slack-web slack-rtm chat chatbots bots chatops
Platform: UNKNOWN
Classifier: Development Status :: 5 - Production/Stable
Classifier: Intended Audience :: Developers
Classifier: Topic :: Communications :: Chat
Classifier: Topic :: System :: Networking
Classifier: Topic :: Office/Business
Classifier: License :: OSI Approved :: MIT License
Classifier: Programming Language :: Python
Classifier: Programming Language :: Python :: 3
Classifier: Programming Language :: Python :: 3.6
Classifier: Programming Language :: Python :: 3.7
Classifier: Programming Language :: Python :: 3.8
Classifier: Programming Language :: Python :: 3.9
Classifier: Programming Language :: Python :: 3.10
Requires-Python: >=3.6.0
Provides-Extra: optional
License-File: LICENSE
